{
"scene_list":[
{
"id":"0",
"charcter1_name":"null",
"charcter1_big_image":"/sp/spacer.png",
"charcter1_small_image":"",
"charcter1_position":"C",
"command1":"fadein",
"effect1":"",
"charcter2_name":"",
"charcter2_big_image":"/sp/spacer.png",
"charcter2_small_image":"",
"charcter2_position":"C",
"command2":"fadein",
"effect2":"",
"charcter3_name":"",
"charcter3_big_image":"",
"charcter3_position":"",
"command3":"next(0.1)",
"effect3":"",
"detail":"",
"bg1":"/sp/quest/scene/bg/bg_5.jpg",
"bg2":"",
"log_image":"",
"bgm":"bgm/03_dungeon_00.mp3",
"voice":"silent",
"se":"",
"sex":"",
"npc_id":"",
"character_id":"",
"character_flag":"",
"sel1_txt":"",
"sel2_txt":"",
"next":"",
"sel_next1":"",
"sel_next2":"",
"synopsis":"桃色の生物を倒した一行。正気を取り戻した村人達は桃色の生物を懲らしめようとするが、美波と志希が間に入って止める。過去にアイドルを目指していた桃色の生物は、オーディションの失敗がきっかけで人間に復讐心を抱き、今回の暴挙に出たのだと言う。既に改心している桃色の生物を、皆は許してあげるのだった。",
"chapter_name":"THE LAST HOPE"
},
{
"id":"1",
"charcter1_name":"桃色の生物",
"charcter1_big_image":"/sp/quest/scene/character/body/3990674000_d.png",
"charcter1_small_image":"",
"charcter1_position":"C",
"command1":"char_vibrate_one",
"effect1":"",
"charcter2_name":"",
"charcter2_big_image":"",
"charcter2_small_image":"",
"charcter2_position":"",
"command2":"",
"effect2":"",
"charcter3_name":"",
"charcter3_big_image":"",
"charcter3_position":"",
"command3":"",
"effect3":"",
"detail":"びっ……びにゃ……",
"bg1":"",
"bg2":"",
"log_image":"",
"bgm":"",
"voice":"voice/scene_evt170609_cp8_q2_s30_1a.mp3",
"se":"",
"sex":"",
"npc_id":"",
"character_id":"",
"character_flag":"",
"sel1_txt":"",
"sel2_txt":"",
"next":"",
"sel_next1":"",
"sel_next2":"",
"synopsis":""
},
{
"id":"2",
"charcter1_name":"null",
"charcter1_big_image":"",
"charcter1_small_image":"",
"charcter1_position":"",
"command1":"fadeout",
"effect1":"",
"charcter2_name":"",
"charcter2_big_image":"/sp/spacer.png",
"charcter2_small_image":"",
"charcter2_position":"C",
"command2":"fadein",
"effect2":"",
"charcter3_name":"",
"charcter3_big_image":"",
"charcter3_position":"",
"command3":"",
"effect3":"",
"detail":"苦しげなうめき声を
漏らす桃色の生物。",
"bg1":"",
"bg2":"",
"log_image":"",
"bgm":"",
"voice":"silent",
"se":"",
"sex":"",
"npc_id":"",
"character_id":"",
"character_flag":"",
"sel1_txt":"",
"sel2_txt":"",
"next":"",
"sel_next1":"",
"sel_next2":"",
"synopsis":""
},
{
"id":"3",
"charcter1_name":"ビィ",
"charcter1_big_image":"",
"charcter1_small_image":"",
"charcter1_position":"",
"command1":"",
"effect1":"",
"charcter2_name":"",
"charcter2_big_image":"/sp/quest/scene/character/body/3050001000_sad.png",
"charcter2_small_image":"",
"charcter2_position":"C",
"command2":"char_vibrate_one",
"effect2":"",
"charcter3_name":"",
"charcter3_big_image":"",
"charcter3_position":"",
"command3":"",
"effect3":"",
"detail":"はぁ……はぁ……
こ、今度こそ……
終わりだよな……",
"bg1":"",
"bg2":"",
"log_image":"",
"bgm":"",
"voice":"voice/scene_evt170609_cp8_q2_s30_3.mp3",
"se":"",
"sex":"",
"npc_id":"",
"character_id":"",
"character_flag":"",
"sel1_txt":"",
"sel2_txt":"",
"next":"",
"sel_next1":"",
"sel_next2":"",
"synopsis":""
},
{
"id":"4",
"charcter1_name":"ルリア",
"charcter1_big_image":"",
"charcter1_small_image":"",
"charcter1_position":"",
"command1":"",
"effect1":"",
"charcter2_name":"",
"charcter2_big_image":"/sp/quest/scene/character/body/3050000000_sad.png",
"charcter2_small_image":"",
"charcter2_position":"C",
"command2":"fadein",
"effect2":"",
"charcter3_name":"",
"charcter3_big_image":"",
"charcter3_position":"",
"command3":"",
"effect3":"",
"detail":"さすがにこの子が割れて
小さいのが出てくるってことは
もう無いですよね？　
",
"bg1":"",
"bg2":"",
"log_image":"",
"bgm":"",
"voice":"voice/scene_evt170609_cp8_q2_s30_4.mp3",
"se":"",
"sex":"",
"npc_id":"",
"character_id":"",
"character_flag":"",
"sel1_txt":"",
"sel2_txt":"",
"next":"",
"sel_next1":"",
"sel_next2":"",
"synopsis":""
},
{
"id":"5",
"charcter1_name":"美波",
"charcter1_big_image":"",
"charcter1_small_image":"",
"charcter1_position":"",
"command1":"",
"effect1":"",
"charcter2_name":"",
"charcter2_big_image":"/sp/quest/scene/character/body/3030193000_serious.png",
"charcter2_small_image":"",
"charcter2_position":"C",
"command2":"fadein",
"effect2":"",
"charcter3_name":"",
"charcter3_big_image":"",
"charcter3_position":"",
"command3":"",
"effect3":"",
"detail":"はい……
もう戦意を失ってるみたいです。",
"bg1":"",
"bg2":"",
"log_image":"",
"bgm":"",
"voice":"voice/scene_evt170609_cp8_q2_s30_5.mp3",
"se":"",
"sex":"",
"npc_id":"",
"character_id":"",
"character_flag":"",
"sel1_txt":"",
"sel2_txt":"",
"next":"",
"sel_next1":"",
"sel_next2":"",
"synopsis":""
},
{
"id":"6",
"charcter1_name":"志希",
"charcter1_big_image":"",
"charcter1_small_image":"",
"charcter1_position":"",
"command1":"",
"effect1":"",
"charcter2_name":"",
"charcter2_big_image":"/sp/quest/scene/character/body/3030194000.png",
"charcter2_small_image":"",
"charcter2_position":"C",
"command2":"fadein",
"effect2":"",
"charcter3_name":"",
"charcter3_big_image":"",
"charcter3_position":"",
"command3":"",
"effect3":"",
"detail":"ふぃー
ようやくこれで終わったみたいだねー",
"bg1":"",
"bg2":"",
"log_image":"",
"bgm":"",
"voice":"voice/scene_evt170609_cp8_q2_s30_6.mp3",
"se":"",
"sex":"",
"npc_id":"",
"character_id":"",
"character_flag":"",
"sel1_txt":"",
"sel2_txt":"",
"next":"",
"sel_next1":"",
"sel_next2":"",
"synopsis":""
},
{
"id":"7",
"charcter1_name":"null",
"charcter1_big_image":"/sp/spacer.png",
"charcter1_small_image":"",
"charcter1_position":"L",
"command1":"fadein",
"effect1":"",
"charcter2_name":"",
"charcter2_big_image":"",
"charcter2_small_image":"",
"charcter2_position":"",
"command2":"fadeout",
"effect2":"",
"charcter3_name":"",
"charcter3_big_image":"/sp/spacer.png",
"charcter3_position":"R",
"command3":"fadein",
"effect3":"",
"detail":"お互いの顔を見合って
安堵の表情を浮かべる
ティード達。",
"bg1":"",
"bg2":"",
"log_image":"",
"bgm":"",
"voice":"silent",
"se":"",
"sex":"",
"npc_id":"",
"character_id":"",
"character_flag":"",
"sel1_txt":"",
"sel2_txt":"",
"next":"",
"sel_next1":"",
"sel_next2":"",
"synopsis":""
},
{
"id":"8",
"charcter1_name":"null",
"charcter1_big_image":"/sp/quest/scene/character/body/3990024000_a.png",
"charcter1_small_image":"",
"charcter1_position":"L",
"command1":"R-slidein",
"effect1":"",
"charcter2_name":"",
"charcter2_big_image":"/sp/spacer.png",
"charcter2_small_image":"",
"charcter2_position":"C",
"command2":"fadein",
"effect2":"",
"charcter3_name":"",
"charcter3_big_image":"/sp/quest/scene/character/body/3990050000.png",
"charcter3_position":"R",
"command3":"R-slidein",
"effect3":"",
"detail":"その時、正気を取り戻した村人達が
桃色の生物の周囲に集まってくる。",
"bg1":"",
"bg2":"",
"log_image":"",
"bgm":"bgm/17_crisis_01.mp3",
"voice":"silent",
"se":"se/run_se_2_2_3c.mp3",
"sex":"",
"npc_id":"",
"character_id":"",
"character_flag":"",
"sel1_txt":"",
"sel2_txt":"",
"next":"",
"sel_next1":"",
"sel_next2":"",
"synopsis":""
},
{
"id":"9",
"charcter1_name":"桃色の生物",
"charcter1_big_image":"/sp/spacer.png",
"charcter1_small_image":"",
"charcter1_position":"C",
"command1":"fadein",
"effect1":"",
"charcter2_name":"",
"charcter2_big_image":"/sp/quest/scene/character/body/3990674000_a.png",
"charcter2_small_image":"",
"charcter2_position":"C",
"command2":"char_vibrate_one",
"effect2":"",
"charcter3_name":"",
"charcter3_big_image":"/sp/spacer.png",
"charcter3_position":"",
"command3":"",
"effect3":"",
"detail":"ぴ……ぴにゃあ……",
"bg1":"",
"bg2":"",
"log_image":"",
"bgm":"",
"voice":"voice/scene_evt170609_cp8_q2_s30_9a.mp3",
"se":"",
"sex":"",
"npc_id":"",
"character_id":"",
"character_flag":"",
"sel1_txt":"",
"sel2_txt":"",
"next":"",
"sel_next1":"",
"sel_next2":"",
"synopsis":""
},
{
"id":"10",
"charcter1_name":"勇敢な青年",
"charcter1_big_image":"/sp/quest/scene/character/body/3990050000.png",
"charcter1_small_image":"",
"charcter1_position":"C",
"command1":"jump",
"effect1":"",
"charcter2_name":"",
"charcter2_big_image":"/sp/spacer.png",
"charcter2_small_image":"",
"charcter2_position":"",
"command2":"",
"effect2":"",
"charcter3_name":"",
"charcter3_big_image":"/sp/spacer.png",
"charcter3_position":"C",
"command3":"fadein",
"effect3":"",
"detail":"くっそー！
よくも好き勝手やってくれたな……
このブサイクな生物めっ！",
"bg1":"",
"bg2":"",
"log_image":"",
"bgm":"",
"voice":"voice/scene_evt170609_cp8_q2_s30_10.mp3",
"se":"",
"sex":"",
"npc_id":"",
"character_id":"",
"character_flag":"",
"sel1_txt":"",
"sel2_txt":"",
"next":"",
"sel_next1":"",
"sel_next2":"",
"synopsis":""
},
{
"id":"11",
"charcter1_name":"過激な青年",
"charcter1_big_image":"/sp/quest/scene/character/body/3990024000_a.png",
"charcter1_small_image":"",
"charcter1_position":"C",
"command1":"fadein",
"effect1":"",
"charcter2_name":"",
"charcter2_big_image":"/sp/spacer.png",
"charcter2_small_image":"",
"charcter2_position":"C",
"command2":"fadein",
"effect2":"",
"charcter3_name":"",
"charcter3_big_image":"",
"charcter3_position":"",
"command3":"",
"effect3":"",
"detail":"覚悟しろよ……
もう二度と悪さしないように
こらしめてやるぜ！",
"bg1":"",
"bg2":"",
"log_image":"",
"bgm":"",
"voice":"voice/scene_evt170609_cp8_q2_s30_11.mp3",
"se":"",
"sex":"",
"npc_id":"",
"character_id":"",
"character_flag":"",
"sel1_txt":"",
"sel2_txt":"",
"next":"",
"sel_next1":"",
"sel_next2":"",
"synopsis":""
},
{
"id":"12",
"charcter1_name":"null",
"charcter1_big_image":"",
"charcter1_small_image":"",
"charcter1_position":"",
"command1":"fadeout",
"effect1":"",
"charcter2_name":"",
"charcter2_big_image":"",
"charcter2_small_image":"",
"charcter2_position":"",
"command2":"vibrate_loop_start",
"effect2":"",
"charcter3_name":"",
"charcter3_big_image":"",
"charcter3_position":"",
"command3":"next(1)",
"effect3":"",
"detail":"",
"bg1":"/sp/quest/scene/bg/bg_5_ef.jpg",
"bg2":"",
"log_image":"",
"bgm":"silent",
"voice":"silent",
"se":"se/scr_war_cry_se_2.mp3",
"sex":"",
"npc_id":"",
"character_id":"",
"character_flag":"",
"sel1_txt":"",
"sel2_txt":"",
"next":"",
"sel_next1":"",
"sel_next2":"",
"synopsis":""
},
{
"id":"13",
"charcter1_name":"桃色の生物",
"charcter1_big_image":"",
"charcter1_small_image":"",
"charcter1_position":"",
"command1":"",
"effect1":"",
"charcter2_name":"",
"charcter2_big_image":"/sp/quest/scene/character/body/3990674000_a.png",
"charcter2_small_image":"",
"charcter2_position":"C",
"command2":"char_vibrate_one",
"effect2":"",
"charcter3_name":"",
"charcter3_big_image":"",
"charcter3_position":"",
"command3":"flash",
"effect3":"",
"detail":"……ぴにゃあ……",
"bg1":"",
"bg2":"",
"log_image":"",
"bgm":"",
"voice":"voice/scene_evt170609_cp8_q2_s30_12a.mp3",
"se":"",
"sex":"",
"npc_id":"",
"character_id":"",
"character_flag":"",
"sel1_txt":"",
"sel2_txt":"",
"next":"",
"sel_next1":"",
"sel_next2":"",
"synopsis":""
},
{
"id":"14",
"charcter1_name":"null",
"charcter1_big_image":"",
"charcter1_small_image":"",
"charcter1_position":"",
"command1":"next(1)",
"effect1":"",
"charcter2_name":"",
"charcter2_big_image":"",
"charcter2_small_image":"",
"charcter2_position":"",
"command2":"vibrate_loop_end",
"effect2":"",
"charcter3_name":"",
"charcter3_big_image":"/sp/quest/scene/character/body/3030193000_angry.png",
"charcter3_position":"C",
"command3":"R-slidein",
"effect3":"",
"detail":"",
"bg1":"/sp/quest/scene/bg/bg_5.jpg",
"bg2":"",
"log_image":"",
"bgm":"silent",
"voice":"silent",
"se":"se/job_vee_se_4_2.mp3",
"sex":"",
"npc_id":"",
"character_id":"",
"character_flag":"",
"sel1_txt":"",
"sel2_txt":"",
"next":"",
"sel_next1":"",
"sel_next2":"",
"synopsis":""
},
{
"id":"15",
"charcter1_name":"美波",
"charcter1_big_image":"",
"charcter1_small_image":"",
"charcter1_position":"",
"command1":"",
"effect1":"",
"charcter2_name":"",
"charcter2_big_image":"",
"charcter2_small_image":"",
"charcter2_position":"",
"command2":"",
"effect2":"",
"charcter3_name":"",
"charcter3_big_image":"",
"charcter3_position":"C",
"command3":"",
"effect3":"",
"detail":"待って！",
"bg1":"",
"bg2":"",
"log_image":"",
"bgm":"",
"voice":"voice/scene_evt170609_cp8_q2_s30_13.mp3",
"se":"",
"sex":"",
"npc_id":"",
"character_id":"",
"character_flag":"",
"sel1_txt":"",
"sel2_txt":"",
"next":"",
"sel_next1":"",
"sel_next2":"",
"synopsis":""
},
{
"id":"16",
"charcter1_name":"null",
"charcter1_big_image":"",
"charcter1_small_image":"",
"charcter1_position":"",
"command1":"",
"effect1":"",
"charcter2_name":"",
"charcter2_big_image":"",
"charcter2_small_image":"",
"charcter2_position":"",
"command2":"fadeout",
"effect2":"",
"charcter3_name":"",
"charcter3_big_image":"",
"charcter3_position":"C",
"command3":"fadeout",
"effect3":"",
"detail":"その時、美波が桃色の生物と
村人達の間に割って入る。",
"bg1":"",
"bg2":"",
"log_image":"",
"bgm":"",
"voice":"silent",
"se":"",
"sex":"",
"npc_id":"",
"character_id":"",
"character_flag":"",
"sel1_txt":"",
"sel2_txt":"",
"next":"",
"sel_next1":"",
"sel_next2":"",
"synopsis":""
},
{
"id":"17",
"charcter1_name":"桃色の生物",
"charcter1_big_image":"/sp/quest/scene/character/body/3990674000_a.png",
"charcter1_small_image":"",
"charcter1_position":"C",
"command1":"fadein",
"effect1":"",
"charcter2_name":"",
"charcter2_big_image":"",
"charcter2_small_image":"",
"charcter2_position":"",
"command2":"flash",
"effect2":"",
"charcter3_name":"",
"charcter3_big_image":"",
"charcter3_position":"",
"command3":"",
"effect3":"",
"detail":"ぴにゃ？",
"bg1":"",
"bg2":"",
"log_image":"",
"bgm":"",
"voice":"voice/scene_evt170609_cp8_q2_s30_15a.mp3",
"se":"",
"sex":"",
"npc_id":"",
"character_id":"",
"character_flag":"",
"sel1_txt":"",
"sel2_txt":"",
"next":"",
"sel_next1":"",
"sel_next2":"",
"synopsis":""
},
{
"id":"18",
"charcter1_name":"過激な青年",
"charcter1_big_image":"/sp/quest/scene/character/body/3990024000_a.png",
"charcter1_small_image":"",
"charcter1_position":"C",
"command1":"fadein",
"effect1":"",
"charcter2_name":"",
"charcter2_big_image":"",
"charcter2_small_image":"",
"charcter2_position":"",
"command2":"",
"effect2":"",
"charcter3_name":"",
"charcter3_big_image":"",
"charcter3_position":"",
"command3":"",
"effect3":"",
"detail":"なっ！　
こりゃ一体何の真似だ！",
"bg1":"",
"bg2":"",
"log_image":"",
"bgm":"bgm/town_men_bgm_1.mp3",
"voice":"voice/scene_evt170609_cp8_q2_s30_16.mp3",
"se":"",
"sex":"",
"npc_id":"",
"character_id":"",
"character_flag":"",
"sel1_txt":"",
"sel2_txt":"",
"next":"",
"sel_next1":"",
"sel_next2":"",
"synopsis":""
},
{
"id":"19",
"charcter1_name":"勇敢な青年",
"charcter1_big_image":"/sp/quest/scene/character/body/3990050000.png",
"charcter1_small_image":"",
"charcter1_position":"C",
"command1":"jump",
"effect1":"",
"charcter2_name":"",
"charcter2_big_image":"",
"charcter2_small_image":"",
"charcter2_position":"",
"command2":"",
"effect2":"",
"charcter3_name":"",
"charcter3_big_image":"",
"charcter3_position":"",
"command3":"",
"effect3":"",
"detail":"ミナミさん、そこをどいて下さい！
その化物が全ての元凶なんですよ！",
"bg1":"",
"bg2":"",
"log_image":"",
"bgm":"",
"voice":"voice/scene_evt170609_cp8_q2_s30_17.mp3",
"se":"",
"sex":"",
"npc_id":"",
"character_id":"",
"character_flag":"",
"sel1_txt":"",
"sel2_txt":"",
"next":"",
"sel_next1":"",
"sel_next2":"",
"synopsis":""
},
{
"id":"20",
"charcter1_name":"美波",
"charcter1_big_image":"/sp/quest/scene/character/body/3030193000_angry.png",
"charcter1_small_image":"",
"charcter1_position":"C",
"command1":"jump",
"effect1":"",
"charcter2_name":"",
"charcter2_big_image":"",
"charcter2_small_image":"",
"charcter2_position":"",
"command2":"",
"effect2":"",
"charcter3_name":"",
"charcter3_big_image":"",
"charcter3_position":"",
"command3":"",
"effect3":"",
"detail":"待って！
この子の話を聞いてあげて下さい！",
"bg1":"",
"bg2":"",
"log_image":"",
"bgm":"",
"voice":"voice/scene_evt170609_cp8_q2_s30_18.mp3",
"se":"se/set_bw_se_1.mp3",
"sex":"",
"npc_id":"",
"character_id":"",
"character_flag":"",
"sel1_txt":"",
"sel2_txt":"",
"next":"",
"sel_next1":"",
"sel_next2":"",
"synopsis":""
},
{
"id":"21",
"charcter1_name":"過激な青年",
"charcter1_big_image":"/sp/quest/scene/character/body/3990024000_a.png",
"charcter1_small_image":"",
"charcter1_position":"C",
"command1":"fadein",
"effect1":"",
"charcter2_name":"",
"charcter2_big_image":"",
"charcter2_small_image":"",
"charcter2_position":"",
"command2":"flash",
"effect2":"",
"charcter3_name":"",
"charcter3_big_image":"",
"charcter3_position":"",
"command3":"",
"effect3":"",
"detail":"話もなにも
ぴにゃぴにゃ言ってる
だけじゃねぇか！",
"bg1":"",
"bg2":"",
"log_image":"",
"bgm":"",
"voice":"voice/scene_evt170609_cp8_q2_s30_19.mp3",
"se":"",
"sex":"",
"npc_id":"",
"character_id":"",
"character_flag":"",
"sel1_txt":"",
"sel2_txt":"",
"next":"",
"sel_next1":"",
"sel_next2":"",
"synopsis":""
},
{
"id":"22",
"charcter1_name":"勇敢な青年",
"charcter1_big_image":"/sp/quest/scene/character/body/3990050000.png",
"charcter1_small_image":"",
"charcter1_position":"C",
"command1":"jump",
"effect1":"",
"charcter2_name":"",
"charcter2_big_image":"",
"charcter2_small_image":"",
"charcter2_position":"",
"command2":"",
"effect2":"",
"charcter3_name":"",
"charcter3_big_image":"",
"charcter3_position":"",
"command3":"",
"effect3":"",
"detail":"ああ！
こればっかりはそいつと同意見です！
そんなヤツ信用なりません！",
"bg1":"",
"bg2":"",
"log_image":"",
"bgm":"",
"voice":"voice/scene_evt170609_cp8_q2_s30_20.mp3",
"se":"",
"sex":"",
"npc_id":"",
"character_id":"",
"character_flag":"",
"sel1_txt":"",
"sel2_txt":"",
"next":"",
"sel_next1":"",
"sel_next2":"",
"synopsis":""
},
{
"id":"23",
"charcter1_name":"志希",
"charcter1_big_image":"/sp/quest/scene/character/body/3030194000.png",
"charcter1_small_image":"",
"charcter1_position":"C",
"command1":"jump",
"effect1":"",
"charcter2_name":"",
"charcter2_big_image":"",
"charcter2_small_image":"",
"charcter2_position":"",
"command2":"",
"effect2":"",
"charcter3_name":"",
"charcter3_big_image":"",
"charcter3_position":"",
"command3":"",
"effect3":"",
"detail":"はいはーい！
志希ちゃんは暴力はんたーい！",
"bg1":"",
"bg2":"",
"log_image":"",
"bgm":"",
"voice":"voice/scene_evt170609_cp8_q2_s30_21.mp3",
"se":"",
"sex":"",
"npc_id":"",
"character_id":"",
"character_flag":"",
"sel1_txt":"",
"sel2_txt":"",
"next":"",
"sel_next1":"",
"sel_next2":"",
"synopsis":""
},
{
"id":"24",
"charcter1_name":"null",
"charcter1_big_image":"",
"charcter1_small_image":"",
"charcter1_position":"",
"command1":"fadeout",
"effect1":"",
"charcter2_name":"",
"charcter2_big_image":"",
"charcter2_small_image":"",
"charcter2_position":"",
"command2":"",
"effect2":"",
"charcter3_name":"",
"charcter3_big_image":"",
"charcter3_position":"",
"command3":"",
"effect3":"",
"detail":"そう言って美波の
隣に並び立つ志希。",
"bg1":"",
"bg2":"",
"log_image":"",
"bgm":"",
"voice":"silent",
"se":"se/walk_se_2_2_3.mp3",
"sex":"",
"npc_id":"",
"character_id":"",
"character_flag":"",
"sel1_txt":"",
"sel2_txt":"",
"next":"",
"sel_next1":"",
"sel_next2":"",
"synopsis":""
},
{
"id":"25",
"charcter1_name":"null",
"charcter1_big_image":"",
"charcter1_small_image":"",
"charcter1_position":"",
"command1":"",
"effect1":"",
"charcter2_name":"",
"charcter2_big_image":"",
"charcter2_small_image":"",
"charcter2_position":"",
"command2":"",
"effect2":"",
"charcter3_name":"",
"charcter3_big_image":"",
"charcter3_position":"",
"command3":"",
"effect3":"",
"detail":"村人達の間に
動揺が巻き起こる。",
"bg1":"",
"bg2":"",
"log_image":"",
"bgm":"",
"voice":"silent",
"se":"se/town_men_bgm_1.mp3",
"sex":"",
"npc_id":"",
"character_id":"",
"character_flag":"",
"sel1_txt":"",
"sel2_txt":"",
"next":"",
"sel_next1":"",
"sel_next2":"",
"synopsis":""
},
{
"id":"26",
"charcter1_name":"勇敢な青年",
"charcter1_big_image":"/sp/quest/scene/character/body/3990050000.png",
"charcter1_small_image":"",
"charcter1_position":"C",
"command1":"fadein",
"effect1":"",
"charcter2_name":"",
"charcter2_big_image":"",
"charcter2_small_image":"",
"charcter2_position":"",
"command2":"",
"effect2":"",
"charcter3_name":"",
"charcter3_big_image":"",
"charcter3_position":"",
"command3":"",
"effect3":"",
"detail":"で、でも……ボス……",
"bg1":"",
"bg2":"",
"log_image":"",
"bgm":"",
"voice":"voice/scene_evt170609_cp8_q2_s30_24.mp3",
"se":"",
"sex":"",
"npc_id":"",
"character_id":"",
"character_flag":"",
"sel1_txt":"",
"sel2_txt":"",
"next":"",
"sel_next1":"",
"sel_next2":"",
"synopsis":""
},
{
"id":"27",
"charcter1_name":"過激な青年",
"charcter1_big_image":"/sp/quest/scene/character/body/3990024000_a.png",
"charcter1_small_image":"",
"charcter1_position":"C",
"command1":"jump",
"effect1":"",
"charcter2_name":"",
"charcter2_big_image":"",
"charcter2_small_image":"",
"charcter2_position":"",
"command2":"",
"effect2":"",
"charcter3_name":"",
"charcter3_big_image":"",
"charcter3_position":"",
"command3":"",
"effect3":"",
"detail":"おいおい！
そいつがまた悪さしたら
どうすんだよ！",
"bg1":"",
"bg2":"",
"log_image":"",
"bgm":"",
"voice":"voice/scene_evt170609_cp8_q2_s30_25.mp3",
"se":"",
"sex":"",
"npc_id":"",
"character_id":"",
"character_flag":"",
"sel1_txt":"",
"sel2_txt":"",
"next":"",
"sel_next1":"",
"sel_next2":"",
"synopsis":""
},
{
"id":"28",
"charcter1_name":"桃色の生物",
"charcter1_big_image":"/sp/quest/scene/character/body/3990674000_a.png",
"charcter1_small_image":"",
"charcter1_position":"C",
"command1":"fadein",
"effect1":"",
"charcter2_name":"",
"charcter2_big_image":"",
"charcter2_small_image":"",
"charcter2_position":"",
"command2":"",
"effect2":"",
"charcter3_name":"",
"charcter3_big_image":"",
"charcter3_position":"",
"command3":"",
"effect3":"",
"detail":"ぴにゃぁぴにゃ……",
"bg1":"",
"bg2":"",
"log_image":"",
"bgm":"bgm/18_rumashi_00a.mp3",
"voice":"voice/scene_evt170609_cp8_q2_s30_26a.mp3",
"se":"se/silent_s1.mp3",
"sex":"",
"npc_id":"",
"character_id":"",
"character_flag":"",
"sel1_txt":"",
"sel2_txt":"",
"next":"",
"sel_next1":"",
"sel_next2":"",
"synopsis":""
},
{
"id":"29",
"charcter1_name":"美波",
"charcter1_big_image":"/sp/quest/scene/character/body/3030193000_laugh3.png",
"charcter1_small_image":"",
"charcter1_position":"C",
"command1":"fadein",
"effect1":"",
"charcter2_name":"",
"charcter2_big_image":"",
"charcter2_small_image":"",
"charcter2_position":"",
"command2":"",
"effect2":"",
"charcter3_name":"",
"charcter3_big_image":"",
"charcter3_position":"",
"command3":"",
"effect3":"",
"detail":"ほら……聞いて下さい。
この通り、本人も
反省してるみたいです。",
"bg1":"",
"bg2":"",
"log_image":"",
"bgm":"",
"voice":"voice/scene_evt170609_cp8_q2_s30_27.mp3",
"se":"",
"sex":"",
"npc_id":"",
"character_id":"",
"character_flag":"",
"sel1_txt":"",
"sel2_txt":"",
"next":"",
"sel_next1":"",
"sel_next2":"",
"synopsis":""
},
{
"id":"30",
"charcter1_name":"桃色の生物",
"charcter1_big_image":"/sp/quest/scene/character/body/3990674000_a.png",
"charcter1_small_image":"",
"charcter1_position":"C",
"command1":"fadein",
"effect1":"",
"charcter2_name":"",
"charcter2_big_image":"",
"charcter2_small_image":"",
"charcter2_position":"",
"command2":"",
"effect2":"",
"charcter3_name":"",
"charcter3_big_image":"",
"charcter3_position":"",
"command3":"",
"effect3":"",
"detail":"ぴにゃ……ぴにゃにゃぴにゃあ……",
"bg1":"",
"bg2":"",
"log_image":"",
"bgm":"",
"voice":"voice/scene_evt170609_cp8_q2_s30_28a.mp3",
"se":"",
"sex":"",
"npc_id":"",
"character_id":"",
"character_flag":"",
"sel1_txt":"",
"sel2_txt":"",
"next":"",
"sel_next1":"",
"sel_next2":"",
"synopsis":""
},
{
"id":"31",
"charcter1_name":"美波",
"charcter1_big_image":"/sp/quest/scene/character/body/3030193000_laugh.png",
"charcter1_small_image":"",
"charcter1_position":"C",
"command1":"fadein",
"effect1":"",
"charcter2_name":"",
"charcter2_big_image":"",
"charcter2_small_image":"",
"charcter2_position":"",
"command2":"",
"effect2":"",
"charcter3_name":"",
"charcter3_big_image":"",
"charcter3_position":"",
"command3":"",
"effect3":"",
"detail":"うん……うんうん。
もう……悪さはしないって
言ってます……",
"bg1":"",
"bg2":"",
"log_image":"",
"bgm":"",
"voice":"voice/scene_evt170609_cp8_q2_s30_29.mp3",
"se":"",
"sex":"",
"npc_id":"",
"character_id":"",
"character_flag":"",
"sel1_txt":"",
"sel2_txt":"",
"next":"",
"sel_next1":"",
"sel_next2":"",
"synopsis":""
},
{
"id":"32",
"charcter1_name":"志希",
"charcter1_big_image":"/sp/quest/scene/character/body/3030194000_laugh.png",
"charcter1_small_image":"",
"charcter1_position":"C",
"command1":"jump",
"effect1":"",
"charcter2_name":"",
"charcter2_big_image":"",
"charcter2_small_image":"",
"charcter2_position":"",
"command2":"",
"effect2":"",
"charcter3_name":"",
"charcter3_big_image":"",
"charcter3_position":"",
"command3":"",
"effect3":"",
"detail":"うんうん、そういってるかもねー！",
"bg1":"",
"bg2":"",
"log_image":"",
"bgm":"",
"voice":"voice/scene_evt170609_cp8_q2_s30_30a.mp3",
"se":"",
"sex":"",
"npc_id":"",
"character_id":"",
"character_flag":"",
"sel1_txt":"",
"sel2_txt":"",
"next":"",
"sel_next1":"",
"sel_next2":"",
"synopsis":""
},
{
"id":"33",
"charcter1_name":"志希",
"charcter1_big_image":"/sp/quest/scene/character/body/3030194000_pride.png",
"charcter1_small_image":"",
"charcter1_position":"",
"command1":"",
"effect1":"",
"charcter2_name":"",
"charcter2_big_image":"",
"charcter2_small_image":"",
"charcter2_position":"",
"command2":"",
"effect2":"",
"charcter3_name":"",
"charcter3_big_image":"",
"charcter3_position":"",
"command3":"",
"effect3":"",
"detail":"……ところで美波ちゃん。
言葉、分かるの？",
"bg1":"",
"bg2":"",
"log_image":"",
"bgm":"",
"voice":"voice/scene_evt170609_cp8_q2_s30_30b.mp3",
"se":"",
"sex":"",
"npc_id":"",
"character_id":"",
"character_flag":"",
"sel1_txt":"",
"sel2_txt":"",
"next":"",
"sel_next1":"",
"sel_next2":"",
"synopsis":""
},
{
"id":"34",
"charcter1_name":"美波",
"charcter1_big_image":"/sp/quest/scene/character/body/3030193000_surprise.png",
"charcter1_small_image":"",
"charcter1_position":"C",
"command1":"fadein",
"effect1":"",
"charcter2_name":"",
"charcter2_big_image":"",
"charcter2_small_image":"",
"charcter2_position":"",
"command2":"",
"effect2":"",
"charcter3_name":"",
"charcter3_big_image":"",
"charcter3_position":"",
"command3":"",
"effect3":"",
"detail":"はい……
なんとなく、ですけど。",
"bg1":"",
"bg2":"",
"log_image":"",
"bgm":"",
"voice":"voice/scene_evt170609_cp8_q2_s30_31.mp3",
"se":"",
"sex":"",
"npc_id":"",
"character_id":"",
"character_flag":"",
"sel1_txt":"",
"sel2_txt":"",
"next":"",
"sel_next1":"",
"sel_next2":"",
"synopsis":""
},
{
"id":"35",
"charcter1_name":"桃色の生物",
"charcter1_big_image":"/sp/quest/scene/character/body/3990674000_b.png",
"charcter1_small_image":"",
"charcter1_position":"C",
"command1":"fadein",
"effect1":"",
"charcter2_name":"",
"charcter2_big_image":"",
"charcter2_small_image":"",
"charcter2_position":"",
"command2":"",
"effect2":"",
"charcter3_name":"",
"charcter3_big_image":"",
"charcter3_position":"",
"command3":"",
"effect3":"",
"detail":"ぴにゃああ……",
"bg1":"",
"bg2":"",
"log_image":"",
"bgm":"",
"voice":"voice/scene_evt170609_cp8_q2_s30_32a.mp3",
"se":"",
"sex":"",
"npc_id":"",
"character_id":"",
"character_flag":"",
"sel1_txt":"",
"sel2_txt":"",
"next":"",
"sel_next1":"",
"sel_next2":"",
"synopsis":""
},
{
"id":"36",
"charcter1_name":"美波",
"charcter1_big_image":"/sp/quest/scene/character/body/3030193000_laugh.png",
"charcter1_small_image":"",
"charcter1_position":"C",
"command1":"fadein",
"effect1":"",
"charcter2_name":"",
"charcter2_big_image":"",
"charcter2_small_image":"",
"charcter2_position":"",
"command2":"",
"effect2":"",
"charcter3_name":"",
"charcter3_big_image":"",
"charcter3_position":"",
"command3":"",
"effect3":"",
"detail":"ありがとう……って。
言ってます。",
"bg1":"",
"bg2":"",
"log_image":"",
"bgm":"",
"voice":"voice/scene_evt170609_cp8_q2_s30_33.mp3",
"se":"",
"sex":"",
"npc_id":"",
"character_id":"",
"character_flag":"",
"sel1_txt":"",
"sel2_txt":"",
"next":"",
"sel_next1":"",
"sel_next2":"",
"synopsis":""
},
{
"id":"37",
"charcter1_name":"null",
"charcter1_big_image":"",
"charcter1_small_image":"",
"charcter1_position":"",
"command1":"fadeout",
"effect1":"",
"charcter2_name":"",
"charcter2_big_image":"",
"charcter2_small_image":"",
"charcter2_position":"",
"command2":"",
"effect2":"",
"charcter3_name":"",
"charcter3_big_image":"",
"charcter3_position":"",
"command3":"",
"effect3":"",
"detail":"桃色の生物と美波は、
目を見合わせる。",
"bg1":"",
"bg2":"",
"log_image":"",
"bgm":"",
"voice":"silent",
"se":"",
"sex":"",
"npc_id":"",
"character_id":"",
"character_flag":"",
"sel1_txt":"",
"sel2_txt":"",
"next":"",
"sel_next1":"",
"sel_next2":"",
"synopsis":""
},
{
"id":"38",
"charcter1_name":"桃色の生物",
"charcter1_big_image":"/sp/quest/scene/character/body/3990674000_a.png",
"charcter1_small_image":"",
"charcter1_position":"C",
"command1":"fadein",
"effect1":"",
"charcter2_name":"",
"charcter2_big_image":"",
"charcter2_small_image":"",
"charcter2_position":"",
"command2":"",
"effect2":"",
"charcter3_name":"",
"charcter3_big_image":"",
"charcter3_position":"",
"command3":"",
"effect3":"",
"detail":"ぴにゃぴにゃ……
ぴにゃにゃ……ぴにゃぴーにゃ。",
"bg1":"",
"bg2":"",
"log_image":"",
"bgm":"bgm/18_rumashi_01a.mp3",
"voice":"voice/scene_evt170609_cp8_q2_s30_35a.mp3",
"se":"",
"sex":"",
"npc_id":"",
"character_id":"",
"character_flag":"",
"sel1_txt":"",
"sel2_txt":"",
"next":"",
"sel_next1":"",
"sel_next2":"",
"synopsis":""
},
{
"id":"39",
"charcter1_name":"美波",
"charcter1_big_image":"/sp/quest/scene/character/body/3030193000_sad.png",
"charcter1_small_image":"",
"charcter1_position":"C",
"command1":"fadein",
"effect1":"",
"charcter2_name":"",
"charcter2_big_image":"",
"charcter2_small_image":"",
"charcter2_position":"",
"command2":"",
"effect2":"",
"charcter3_name":"",
"charcter3_big_image":"",
"charcter3_position":"",
"command3":"",
"effect3":"",
"detail":"その……
この子は、アイドルに
憧れていたんです。",
"bg1":"",
"bg2":"",
"log_image":"",
"bgm":"",
"voice":"voice/scene_evt170609_cp8_q2_s30_36.mp3",
"se":"",
"sex":"",
"npc_id":"",
"character_id":"",
"character_flag":"",
"sel1_txt":"",
"sel2_txt":"",
"next":"",
"sel_next1":"",
"sel_next2":"",
"synopsis":""
},
{
"id":"40",
"charcter1_name":"美波",
"charcter1_big_image":"",
"charcter1_small_image":"",
"charcter1_position":"",
"command1":"",
"effect1":"",
"charcter2_name":"",
"charcter2_big_image":"",
"charcter2_small_image":"",
"charcter2_position":"",
"command2":"",
"effect2":"",
"charcter3_name":"",
"charcter3_big_image":"",
"charcter3_position":"",
"command3":"",
"effect3":"",
"detail":"でも、すごく恥ずかしがり屋な性格が
災いして、以前にオーディションで
大失敗をしてしまったそうです。",
"bg1":"",
"bg2":"",
"log_image":"",
"bgm":"",
"voice":"voice/scene_evt170609_cp8_q2_s30_37.mp3",
"se":"",
"sex":"",
"npc_id":"",
"character_id":"",
"character_flag":"",
"sel1_txt":"",
"sel2_txt":"",
"next":"",
"sel_next1":"",
"sel_next2":"",
"synopsis":""
},
{
"id":"41",
"charcter1_name":"桃色の生物",
"charcter1_big_image":"/sp/quest/scene/character/body/3990674000_a.png",
"charcter1_small_image":"",
"charcter1_position":"C",
"command1":"jump",
"effect1":"",
"charcter2_name":"",
"charcter2_big_image":"",
"charcter2_small_image":"",
"charcter2_position":"",
"command2":"",
"effect2":"",
"charcter3_name":"",
"charcter3_big_image":"",
"charcter3_position":"",
"command3":"",
"effect3":"",
"detail":"ぴにゃっぴ！
にゃにゃぴーにゃ、ぴにゃぴ。",
"bg1":"",
"bg2":"",
"log_image":"",
"bgm":"",
"voice":"voice/scene_evt170609_cp8_q2_s30_38a.mp3",
"se":"",
"sex":"",
"npc_id":"",
"character_id":"",
"character_flag":"",
"sel1_txt":"",
"sel2_txt":"",
"next":"",
"sel_next1":"",
"sel_next2":"",
"synopsis":""
},
{
"id":"42",
"charcter1_name":"美波",
"charcter1_big_image":"/sp/quest/scene/character/body/3030193000_serious.png",
"charcter1_small_image":"",
"charcter1_position":"C",
"command1":"fadein",
"effect1":"",
"charcter2_name":"",
"charcter2_big_image":"",
"charcter2_small_image":"",
"charcter2_position":"",
"command2":"",
"effect2":"",
"charcter3_name":"",
"charcter3_big_image":"",
"charcter3_position":"",
"command3":"",
"effect3":"",
"detail":"それで落ち込んでいる時に、
山奥の廃寺で仏像を見つけて、
試しにそれを被ってみたそうです。",
"bg1":"",
"bg2":"",
"log_image":"",
"bgm":"",
"voice":"voice/scene_evt170609_cp8_q2_s30_39.mp3",
"se":"",
"sex":"",
"npc_id":"",
"character_id":"",
"character_flag":"",
"sel1_txt":"",
"sel2_txt":"",
"next":"",
"sel_next1":"",
"sel_next2":"",
"synopsis":""
},
{
"id":"43",
"charcter1_name":"美波",
"charcter1_big_image":"",
"charcter1_small_image":"",
"charcter1_position":"",
"command1":"",
"effect1":"",
"charcter2_name":"",
"charcter2_big_image":"",
"charcter2_small_image":"",
"charcter2_position":"",
"command2":"",
"effect2":"",
"charcter3_name":"",
"charcter3_big_image":"",
"charcter3_position":"",
"command3":"",
"effect3":"",
"detail":"そうしたら、仏像越しに段々と
人目に慣れていって、本来の実力を
出すことができる様になったそうです。",
"bg1":"",
"bg2":"",
"log_image":"",
"bgm":"",
"voice":"voice/scene_evt170609_cp8_q2_s30_40.mp3",
"se":"",
"sex":"",
"npc_id":"",
"character_id":"",
"character_flag":"",
"sel1_txt":"",
"sel2_txt":"",
"next":"",
"sel_next1":"",
"sel_next2":"",
"synopsis":""
},
{
"id":"44",
"charcter1_name":"桃色の生物",
"charcter1_big_image":"/sp/quest/scene/character/body/3990674000_a.png",
"charcter1_small_image":"",
"charcter1_position":"C",
"command1":"fadein",
"effect1":"",
"charcter2_name":"",
"charcter2_big_image":"",
"charcter2_small_image":"",
"charcter2_position":"",
"command2":"",
"effect2":"",
"charcter3_name":"",
"charcter3_big_image":"",
"charcter3_position":"",
"command3":"",
"effect3":"",
"detail":"ぴにゃ……ぴにゃぴ？
ぴにゃぴにゃ……ぴにゃ……",
"bg1":"",
"bg2":"",
"log_image":"",
"bgm":"",
"voice":"voice/scene_evt170609_cp8_q2_s30_41a.mp3",
"se":"",
"sex":"",
"npc_id":"",
"character_id":"",
"character_flag":"",
"sel1_txt":"",
"sel2_txt":"",
"next":"",
"sel_next1":"",
"sel_next2":"",
"synopsis":""
},
{
"id":"45",
"charcter1_name":"美波",
"charcter1_big_image":"/sp/quest/scene/character/body/3030193000_sad.png",
"charcter1_small_image":"",
"charcter1_position":"C",
"command1":"fadein",
"effect1":"",
"charcter2_name":"",
"charcter2_big_image":"",
"charcter2_small_image":"",
"charcter2_position":"",
"command2":"",
"effect2":"",
"charcter3_name":"",
"charcter3_big_image":"",
"charcter3_position":"",
"command3":"",
"effect3":"",
"detail":"そこから先は、自分を馬鹿にした
人間への復讐心から、力を使って
悪さに手を染めてしまったそうで……",
"bg1":"",
"bg2":"",
"log_image":"",
"bgm":"",
"voice":"voice/scene_evt170609_cp8_q2_s30_42.mp3",
"se":"",
"sex":"",
"npc_id":"",
"character_id":"",
"character_flag":"",
"sel1_txt":"",
"sel2_txt":"",
"next":"",
"sel_next1":"",
"sel_next2":"",
"synopsis":""
},
{
"id":"46",
"charcter1_name":"美波",
"charcter1_big_image":"",
"charcter1_small_image":"",
"charcter1_position":"",
"command1":"",
"effect1":"",
"charcter2_name":"",
"charcter2_big_image":"",
"charcter2_small_image":"",
"charcter2_position":"",
"command2":"",
"effect2":"",
"charcter3_name":"",
"charcter3_big_image":"",
"charcter3_position":"",
"command3":"",
"effect3":"",
"detail":"その力が、今回のぴにゃビ化騒動の
発端になってしまったようです。",
"bg1":"",
"bg2":"",
"log_image":"",
"bgm":"",
"voice":"voice/scene_evt170609_cp8_q2_s30_43.mp3",
"se":"",
"sex":"",
"npc_id":"",
"character_id":"",
"character_flag":"",
"sel1_txt":"",
"sel2_txt":"",
"next":"",
"sel_next1":"",
"sel_next2":"",
"synopsis":""
},
{
"id":"47",
"charcter1_name":"桃色の生物",
"charcter1_big_image":"/sp/quest/scene/character/body/3990674000_a.png",
"charcter1_small_image":"",
"charcter1_position":"C",
"command1":"fadein",
"effect1":"",
"charcter2_name":"",
"charcter2_big_image":"",
"charcter2_small_image":"",
"charcter2_position":"",
"command2":"",
"effect2":"",
"charcter3_name":"",
"charcter3_big_image":"",
"charcter3_position":"",
"command3":"",
"effect3":"",
"detail":"ぴにゃにゃにゃぴぃ……",
"bg1":"",
"bg2":"",
"log_image":"",
"bgm":"",
"voice":"voice/scene_evt170609_cp8_q2_s30_44a.mp3",
"se":"",
"sex":"",
"npc_id":"",
"character_id":"",
"character_flag":"",
"sel1_txt":"",
"sel2_txt":"",
"next":"",
"sel_next1":"",
"sel_next2":"",
"synopsis":""
},
{
"id":"48",
"charcter1_name":"美波",
"charcter1_big_image":"/sp/quest/scene/character/body/3030193000_think.png",
"charcter1_small_image":"",
"charcter1_position":"C",
"command1":"fadein",
"effect1":"",
"charcter2_name":"",
"charcter2_big_image":"",
"charcter2_small_image":"",
"charcter2_position":"",
"command2":"",
"effect2":"",
"charcter3_name":"",
"charcter3_big_image":"",
"charcter3_position":"",
"command3":"",
"effect3":"",
"detail":"でも、この通り、
彼女も反省しているそうです。",
"bg1":"",
"bg2":"",
"log_image":"",
"bgm":"",
"voice":"voice/scene_evt170609_cp8_q2_s30_45.mp3",
"se":"",
"sex":"",
"npc_id":"",
"character_id":"",
"character_flag":"",
"sel1_txt":"",
"sel2_txt":"",
"next":"",
"sel_next1":"",
"sel_next2":"",
"synopsis":""
},
{
"id":"49",
"charcter1_name":"桃色の生物",
"charcter1_big_image":"/sp/quest/scene/character/body/3990674000_a.png",
"charcter1_small_image":"",
"charcter1_position":"C",
"command1":"char_vibrate_one",
"effect1":"",
"charcter2_name":"",
"charcter2_big_image":"",
"charcter2_small_image":"",
"charcter2_position":"",
"command2":"",
"effect2":"",
"charcter3_name":"",
"charcter3_big_image":"",
"charcter3_position":"",
"command3":"",
"effect3":"",
"detail":"ぴっ……ぴっ……
ぴいにゃにゃぴにゃ……",
"bg1":"",
"bg2":"",
"log_image":"",
"bgm":"",
"voice":"voice/scene_evt170609_cp8_q2_s30_46a.mp3",
"se":"",
"sex":"",
"npc_id":"",
"character_id":"",
"character_flag":"",
"sel1_txt":"",
"sel2_txt":"",
"next":"",
"sel_next1":"",
"sel_next2":"",
"synopsis":""
},
{
"id":"50",
"charcter1_name":"美波",
"charcter1_big_image":"/sp/quest/scene/character/body/3030193000_sad.png",
"charcter1_small_image":"",
"charcter1_position":"C",
"command1":"fadein",
"effect1":"",
"charcter2_name":"",
"charcter2_big_image":"",
"charcter2_small_image":"",
"charcter2_position":"",
"command2":"",
"effect2":"",
"charcter3_name":"",
"charcter3_big_image":"",
"charcter3_position":"",
"command3":"",
"effect3":"",
"detail":"ごめんなさいって。
もう二度とこんなことはしないので、
許して欲しいって、謝ってます。",
"bg1":"",
"bg2":"",
"log_image":"",
"bgm":"",
"voice":"voice/scene_evt170609_cp8_q2_s30_47.mp3",
"se":"",
"sex":"",
"npc_id":"",
"character_id":"",
"character_flag":"",
"sel1_txt":"",
"sel2_txt":"",
"next":"",
"sel_next1":"",
"sel_next2":"",
"synopsis":""
},
{
"id":"51",
"charcter1_name":"null",
"charcter1_big_image":"",
"charcter1_small_image":"",
"charcter1_position":"",
"command1":"fadeout",
"effect1":"",
"charcter2_name":"",
"charcter2_big_image":"",
"charcter2_small_image":"",
"charcter2_position":"",
"command2":"",
"effect2":"",
"charcter3_name":"",
"charcter3_big_image":"/sp/quest/scene/character/body/shadow60.png",
"charcter3_position":"C",
"command3":"fadein",
"effect3":"",
"detail":"美波と桃色の生物から
想いの丈をぶつけられた
その場の人々。",
"bg1":"",
"bg2":"",
"log_image":"",
"bgm":"",
"voice":"silent",
"se":"",
"sex":"",
"npc_id":"",
"character_id":"",
"character_flag":"",
"sel1_txt":"",
"sel2_txt":"",
"next":"",
"sel_next1":"",
"sel_next2":"",
"synopsis":""
},
{
"id":"52",
"charcter1_name":"null",
"charcter1_big_image":"",
"charcter1_small_image":"",
"charcter1_position":"",
"command1":"",
"effect1":"",
"charcter2_name":"",
"charcter2_big_image":"",
"charcter2_small_image":"",
"charcter2_position":"",
"command2":"",
"effect2":"",
"charcter3_name":"",
"charcter3_big_image":"",
"charcter3_position":"",
"command3":"",
"effect3":"",
"detail":"その場に立ち込めていた
剣呑な空気は、次第に
和らいで行くのだった。",
"bg1":"",
"bg2":"",
"log_image":"",
"bgm":"bgm/18_rumashi_03a.mp3",
"voice":"silent",
"se":"",
"sex":"",
"npc_id":"",
"character_id":"",
"character_flag":"",
"sel1_txt":"",
"sel2_txt":"",
"next":"",
"sel_next1":"",
"sel_next2":"",
"synopsis":""
},
{
"id":"53",
"charcter1_name":"過激な青年",
"charcter1_big_image":"/sp/quest/scene/character/body/3990024000_a.png",
"charcter1_small_image":"",
"charcter1_position":"C",
"command1":"fadein",
"effect1":"",
"charcter2_name":"",
"charcter2_big_image":"",
"charcter2_small_image":"",
"charcter2_position":"",
"command2":"",
"effect2":"",
"charcter3_name":"",
"charcter3_big_image":"",
"charcter3_position":"",
"command3":"fadeout",
"effect3":"",
"detail":"ふっ……
そこまで言われちゃしかたねぇな。",
"bg1":"",
"bg2":"",
"log_image":"",
"bgm":"",
"voice":"voice/scene_evt170609_cp8_q2_s30_50.mp3",
"se":"",
"sex":"",
"npc_id":"",
"character_id":"",
"character_flag":"",
"sel1_txt":"",
"sel2_txt":"",
"next":"",
"sel_next1":"",
"sel_next2":"",
"synopsis":""
},
{
"id":"54",
"charcter1_name":"勇敢な青年",
"charcter1_big_image":"/sp/quest/scene/character/body/3990050000.png",
"charcter1_small_image":"",
"charcter1_position":"C",
"command1":"fadein",
"effect1":"",
"charcter2_name":"",
"charcter2_big_image":"",
"charcter2_small_image":"",
"charcter2_position":"",
"command2":"",
"effect2":"",
"charcter3_name":"",
"charcter3_big_image":"",
"charcter3_position":"",
"command3":"",
"effect3":"",
"detail":"ああ……
アイドルの卵を潰してもいい、
なんてこの口が裂けても言えねぇ。",
"bg1":"",
"bg2":"",
"log_image":"",
"bgm":"",
"voice":"voice/scene_evt170609_cp8_q2_s30_51.mp3",
"se":"",
"sex":"",
"npc_id":"",
"character_id":"",
"character_flag":"",
"sel1_txt":"",
"sel2_txt":"",
"next":"",
"sel_next1":"",
"sel_next2":"",
"synopsis":""
},
{
"id":"55",
"charcter1_name":"null",
"charcter1_big_image":"",
"charcter1_small_image":"",
"charcter1_position":"",
"command1":"fadeout",
"effect1":"",
"charcter2_name":"",
"charcter2_big_image":"",
"charcter2_small_image":"",
"charcter2_position":"",
"command2":"",
"effect2":"",
"charcter3_name":"",
"charcter3_big_image":"",
"charcter3_position":"",
"command3":"",
"effect3":"",
"detail":"美波の熱のこもった言葉によって
村人達は桃色の生物を許すのだった。",
"bg1":"",
"bg2":"",
"log_image":"",
"bgm":"",
"voice":"silent",
"se":"",
"sex":"",
"npc_id":"",
"character_id":"",
"character_flag":"",
"sel1_txt":"",
"sel2_txt":"",
"next":"",
"sel_next1":"",
"sel_next2":"",
"synopsis":""
},
{
"id":"56",
"charcter1_name":"桃色の生物",
"charcter1_big_image":"/sp/quest/scene/character/body/3990674000_a.png",
"charcter1_small_image":"",
"charcter1_position":"C",
"command1":"fadein",
"effect1":"",
"charcter2_name":"",
"charcter2_big_image":"",
"charcter2_small_image":"",
"charcter2_position":"",
"command2":"",
"effect2":"",
"charcter3_name":"",
"charcter3_big_image":"",
"charcter3_position":"",
"command3":"",
"effect3":"",
"detail":"ぴにゃあ……？",
"bg1":"",
"bg2":"",
"log_image":"",
"bgm":"",
"voice":"voice/scene_evt170609_cp8_q2_s30_53a.mp3",
"se":"",
"sex":"",
"npc_id":"",
"character_id":"",
"character_flag":"",
"sel1_txt":"",
"sel2_txt":"",
"next":"",
"sel_next1":"",
"sel_next2":"",
"synopsis":""
},
{
"id":"57",
"charcter1_name":"美波",
"charcter1_big_image":"/sp/quest/scene/character/body/3030193000_laugh2.png",
"charcter1_small_image":"",
"charcter1_position":"C",
"command1":"jump",
"effect1":"",
"charcter2_name":"",
"charcter2_big_image":"",
"charcter2_small_image":"",
"charcter2_position":"",
"command2":"flash",
"effect2":"",
"charcter3_name":"",
"charcter3_big_image":"",
"charcter3_position":"",
"command3":"",
"effect3":"",
"detail":"うん、許してくれるって！",
"bg1":"",
"bg2":"",
"log_image":"",
"bgm":"",
"voice":"voice/scene_evt170609_cp8_q2_s30_54.mp3",
"se":"se/set_bw_se_1.mp3",
"sex":"",
"npc_id":"",
"character_id":"",
"character_flag":"",
"sel1_txt":"",
"sel2_txt":"",
"next":"",
"sel_next1":"",
"sel_next2":"",
"synopsis":""
},
{
"id":"58",
"charcter1_name":"志希",
"charcter1_big_image":"/sp/quest/scene/character/body/3030194000_laugh.png",
"charcter1_small_image":"",
"charcter1_position":"C",
"command1":"fadein",
"effect1":"",
"charcter2_name":"",
"charcter2_big_image":"",
"charcter2_small_image":"",
"charcter2_position":"",
"command2":"",
"effect2":"",
"charcter3_name":"",
"charcter3_big_image":"",
"charcter3_position":"",
"command3":"",
"effect3":"",
"detail":"まー、何はともあれ、
これで事件も一件落着だね！",
"bg1":"",
"bg2":"",
"log_image":"",
"bgm":"",
"voice":"voice/scene_evt170609_cp8_q2_s30_55.mp3",
"se":"",
"sex":"",
"npc_id":"",
"character_id":"",
"character_flag":"",
"sel1_txt":"",
"sel2_txt":"",
"next":"",
"sel_next1":"",
"sel_next2":"",
"synopsis":""
},
{
"id":"59",
"charcter1_name":"ビィ",
"charcter1_big_image":"/sp/quest/scene/character/body/3050001000_mood.png",
"charcter1_small_image":"",
"charcter1_position":"C",
"command1":"fadein",
"effect1":"",
"charcter2_name":"",
"charcter2_big_image":"",
"charcter2_small_image":"",
"charcter2_position":"",
"command2":"",
"effect2":"",
"charcter3_name":"",
"charcter3_big_image":"",
"charcter3_position":"",
"command3":"",
"effect3":"",
"detail":"ああ……
なんか良くわかんねぇけど、
無事に解決して良かったな。",
"bg1":"",
"bg2":"",
"log_image":"",
"bgm":"",
"voice":"voice/scene_evt170609_cp8_q2_s30_56.mp3",
"se":"",
"sex":"",
"npc_id":"",
"character_id":"",
"character_flag":"",
"sel1_txt":"",
"sel2_txt":"",
"next":"",
"sel_next1":"",
"sel_next2":"",
"synopsis":""
},
{
"id":"60",
"charcter1_name":"ルリア",
"charcter1_big_image":"/sp/quest/scene/character/body/3050000000_sad.png",
"charcter1_small_image":"",
"charcter1_position":"C",
"command1":"fadein",
"effect1":"",
"charcter2_name":"",
"charcter2_big_image":"",
"charcter2_small_image":"",
"charcter2_position":"",
"command2":"",
"effect2":"",
"charcter3_name":"",
"charcter3_big_image":"",
"charcter3_position":"",
"command3":"",
"effect3":"",
"detail":"うぅ……
本当に良かったです。",
"bg1":"",
"bg2":"",
"log_image":"",
"bgm":"",
"voice":"voice/scene_evt170609_cp8_q2_s30_57.mp3",
"se":"",
"sex":"",
"npc_id":"",
"character_id":"",
"character_flag":"",
"sel1_txt":"",
"sel2_txt":"",
"next":"",
"sel_next1":"",
"sel_next2":"",
"synopsis":""
},
{
"id":"61",
"charcter1_name":"null",
"charcter1_big_image":"",
"charcter1_small_image":"",
"charcter1_position":"",
"command1":"fadeout",
"effect1":"",
"charcter2_name":"",
"charcter2_big_image":"",
"charcter2_small_image":"",
"charcter2_position":"",
"command2":"",
"effect2":"",
"charcter3_name":"",
"charcter3_big_image":"/sp/quest/scene/character/body/3990403000.png",
"charcter3_position":"C",
"command3":"fadein",
"effect3":"",
"detail":"ぴにゃビ化事件を解決して、
満足気なティード。",
"bg1":"",
"bg2":"",
"log_image":"",
"bgm":"",
"voice":"silent",
"se":"",
"sex":"",
"npc_id":"",
"character_id":"",
"character_flag":"",
"sel1_txt":"",
"sel2_txt":"",
"next":"",
"sel_next1":"",
"sel_next2":"",
"synopsis":""
},
{
"id":"62",
"charcter1_name":"ビィ",
"charcter1_big_image":"/sp/quest/scene/character/body/3050001000.png",
"charcter1_small_image":"",
"charcter1_position":"C",
"command1":"fadein",
"effect1":"",
"charcter2_name":"",
"charcter2_big_image":"",
"charcter2_small_image":"",
"charcter2_position":"",
"command2":"flash",
"effect2":"",
"charcter3_name":"",
"charcter3_big_image":"",
"charcter3_position":"",
"command3":"fadeout",
"effect3":"",
"detail":"あれ……待てよ……
でもぴにゃビ化したまんまの人が
まだ残ってるんじゃねぇのか？",
"bg1":"",
"bg2":"",
"log_image":"",
"bgm":"bgm/18_rumashi_04a.mp3",
"voice":"voice/scene_evt170609_cp8_q2_s30_59.mp3",
"se":"",
"sex":"",
"npc_id":"",
"character_id":"",
"character_flag":"",
"sel1_txt":"",
"sel2_txt":"",
"next":"",
"sel_next1":"",
"sel_next2":"",
"synopsis":""
},
{
"id":"63",
"charcter1_name":"ルリア",
"charcter1_big_image":"/sp/quest/scene/character/body/3050000000_surprise.png",
"charcter1_small_image":"",
"charcter1_position":"C",
"command1":"jump",
"effect1":"",
"charcter2_name":"",
"charcter2_big_image":"",
"charcter2_small_image":"",
"charcter2_position":"",
"command2":"",
"effect2":"",
"charcter3_name":"",
"charcter3_big_image":"",
"charcter3_position":"",
"command3":"",
"effect3":"",
"detail":"わわわ！　そうでした！
その子の力で止めることは
できないんでしょうか？",
"bg1":"",
"bg2":"",
"log_image":"",
"bgm":"",
"voice":"voice/scene_evt170609_cp8_q2_s30_60.mp3",
"se":"",
"sex":"",
"npc_id":"",
"character_id":"",
"character_flag":"",
"sel1_txt":"",
"sel2_txt":"",
"next":"",
"sel_next1":"",
"sel_next2":"",
"synopsis":""
},
{
"id":"64",
"charcter1_name":"桃色の生物",
"charcter1_big_image":"/sp/quest/scene/character/body/3990674000_a.png",
"charcter1_small_image":"",
"charcter1_position":"C",
"command1":"fadein",
"effect1":"",
"charcter2_name":"",
"charcter2_big_image":"",
"charcter2_small_image":"",
"charcter2_position":"",
"command2":"",
"effect2":"",
"charcter3_name":"",
"charcter3_big_image":"",
"charcter3_position":"",
"command3":"",
"effect3":"",
"detail":"ぴにゃあ……",
"bg1":"",
"bg2":"",
"log_image":"",
"bgm":"",
"voice":"voice/scene_evt170609_cp8_q2_s30_61a.mp3",
"se":"",
"sex":"",
"npc_id":"",
"character_id":"",
"character_flag":"",
"sel1_txt":"",
"sel2_txt":"",
"next":"",
"sel_next1":"",
"sel_next2":"",
"synopsis":""
},
{
"id":"65",
"charcter1_name":"美波",
"charcter1_big_image":"/sp/quest/scene/character/body/3030193000_think.png",
"charcter1_small_image":"",
"charcter1_position":"C",
"command1":"fadein",
"effect1":"",
"charcter2_name":"",
"charcter2_big_image":"",
"charcter2_small_image":"",
"charcter2_position":"",
"command2":"",
"effect2":"",
"charcter3_name":"",
"charcter3_big_image":"",
"charcter3_position":"",
"command3":"",
"effect3":"",
"detail":"一度広がってしまった靄は、
止められないそうです……",
"bg1":"",
"bg2":"",
"log_image":"",
"bgm":"",
"voice":"voice/scene_evt170609_cp8_q2_s30_62.mp3",
"se":"",
"sex":"",
"npc_id":"",
"character_id":"",
"character_flag":"",
"sel1_txt":"",
"sel2_txt":"",
"next":"",
"sel_next1":"",
"sel_next2":"",
"synopsis":""
},
{
"id":"66",
"charcter1_name":"志希",
"charcter1_big_image":"/sp/quest/scene/character/body/3030194000.png",
"charcter1_small_image":"",
"charcter1_position":"C",
"command1":"jump",
"effect1":"",
"charcter2_name":"",
"charcter2_big_image":"",
"charcter2_small_image":"",
"charcter2_position":"",
"command2":"flash",
"effect2":"",
"charcter3_name":"",
"charcter3_big_image":"",
"charcter3_position":"",
"command3":"",
"effect3":"",
"detail":"ならあたしが「AMIBO」を
大量生産するから、
それを騎空艇から撒いちゃえ！",
"bg1":"",
"bg2":"",
"log_image":"",
"bgm":"",
"voice":"voice/scene_evt170609_cp8_q2_s30_63.mp3",
"se":"se/ougi_gauge_se_1.mp3",
"sex":"",
"npc_id":"",
"character_id":"",
"character_flag":"",
"sel1_txt":"",
"sel2_txt":"",
"next":"",
"sel_next1":"",
"sel_next2":"",
"synopsis":""
},
{
"id":"67",
"charcter1_name":"ビィ",
"charcter1_big_image":"/sp/quest/scene/character/body/3050001000_mood.png",
"charcter1_small_image":"",
"charcter1_position":"C",
"command1":"jump",
"effect1":"",
"charcter2_name":"",
"charcter2_big_image":"",
"charcter2_small_image":"",
"charcter2_position":"",
"command2":"",
"effect2":"",
"charcter3_name":"",
"charcter3_big_image":"",
"charcter3_position":"",
"command3":"",
"effect3":"",
"detail":"おっ！
そりゃいいアイデアだな！",
"bg1":"",
"bg2":"",
"log_image":"",
"bgm":"",
"voice":"voice/scene_evt170609_cp8_q2_s30_64.mp3",
"se":"",
"sex":"",
"npc_id":"",
"character_id":"",
"character_flag":"",
"sel1_txt":"",
"sel2_txt":"",
"next":"",
"sel_next1":"",
"sel_next2":"",
"synopsis":""
},
{
"id":"68",
"charcter1_name":"ルリア",
"charcter1_big_image":"/sp/quest/scene/character/body/3050000000_joy.png",
"charcter1_small_image":"",
"charcter1_position":"C",
"command1":"jump",
"effect1":"",
"charcter2_name":"",
"charcter2_big_image":"",
"charcter2_small_image":"",
"charcter2_position":"",
"command2":"",
"effect2":"",
"charcter3_name":"",
"charcter3_big_image":"",
"charcter3_position":"",
"command3":"",
"effect3":"",
"detail":"はい！　そうと決まれば、
さっそくみんなで準備しましょう！",
"bg1":"",
"bg2":"",
"log_image":"",
"bgm":"",
"voice":"voice/scene_evt170609_cp8_q2_s30_65.mp3",
"se":"",
"sex":"",
"npc_id":"",
"character_id":"",
"character_flag":"",
"sel1_txt":"",
"sel2_txt":"",
"next":"",
"sel_next1":"",
"sel_next2":"",
"synopsis":""
},
{
"id":"69",
"charcter1_name":"null",
"charcter1_big_image":"",
"charcter1_small_image":"",
"charcter1_position":"",
"command1":"",
"effect1":"",
"charcter2_name":"",
"charcter2_big_image":"",
"charcter2_small_image":"",
"charcter2_position":"",
"command2":"color_fadein(0,0,0,1,2s)",
"effect2":"",
"charcter3_name":"",
"charcter3_big_image":"",
"charcter3_position":"",
"command3":"",
"effect3":"",
"detail":"村人達とティード一行は
協力して「AMIBO」を散布する
段取りを整えていくのだった。",
"bg1":"",
"bg2":"",
"log_image":"",
"bgm":"",
"voice":"silent",
"se":"",
"sex":"",
"npc_id":"",
"character_id":"",
"character_flag":"",
"sel1_txt":"",
"sel2_txt":"",
"next":"",
"sel_next1":"",
"sel_next2":"",
"synopsis":""
},
{
"id":"70",
"charcter1_name":"null",
"charcter1_big_image":"",
"charcter1_small_image":"",
"charcter1_position":"",
"command1":"",
"effect1":"",
"charcter2_name":"",
"charcter2_big_image":"",
"charcter2_small_image":"",
"charcter2_position":"",
"command2":"color_fadein(1,1,0,1,1s)",
"effect2":"",
"charcter3_name":"",
"charcter3_big_image":"",
"charcter3_position":"",
"command3":"next(1)",
"effect3":"",
"detail":"",
"bg1":"",
"bg2":"",
"log_image":"",
"bgm":"",
"voice":"silent",
"se":"",
"sex":"",
"npc_id":"",
"character_id":"",
"character_flag":"",
"sel1_txt":"",
"sel2_txt":"",
"next":"",
"sel_next1":"",
"sel_next2":"",
"synopsis":""
},
{
"id":"71",
"charcter1_name":"null",
"charcter1_big_image":"",
"charcter1_small_image":"",
"charcter1_position":"",
"command1":"",
"effect1":"",
"charcter2_name":"",
"charcter2_big_image":"",
"charcter2_small_image":"",
"charcter2_position":"",
"command2":"color_fadein(1,1,1,1,0.5s)",
"effect2":"",
"charcter3_name":"",
"charcter3_big_image":"",
"charcter3_position":"",
"command3":"next(0.5)",
"effect3":"",
"detail":"",
"bg1":"",
"bg2":"",
"log_image":"",
"bgm":"",
"voice":"silent",
"se":"",
"sex":"",
"npc_id":"",
"character_id":"",
"character_flag":"",
"sel1_txt":"",
"sel2_txt":"",
"next":"",
"sel_next1":"",
"sel_next2":"",
"synopsis":""
},
{
"id":"72",
"charcter1_name":"null",
"charcter1_big_image":"",
"charcter1_small_image":"",
"charcter1_position":"",
"command1":"",
"effect1":"",
"charcter2_name":"",
"charcter2_big_image":"",
"charcter2_small_image":"",
"charcter2_position":"",
"command2":"color_fadein(0,0,0,1,0.2s)",
"effect2":"",
"charcter3_name":"",
"charcter3_big_image":"",
"charcter3_position":"",
"command3":"next(1)",
"effect3":"",
"detail":"",
"bg1":"",
"bg2":"",
"log_image":"",
"bgm":"",
"voice":"silent",
"se":"",
"sex":"",
"npc_id":"",
"character_id":"",
"character_flag":"",
"sel1_txt":"",
"sel2_txt":"",
"next":"",
"sel_next1":"",
"sel_next2":"",
"synopsis":""
},
{
"id":"73",
"charcter1_name":"null",
"charcter1_big_image":"/sp/spacer.png",
"charcter1_small_image":"",
"charcter1_position":"C",
"command1":"fadein",
"effect1":"",
"charcter2_name":"",
"charcter2_big_image":"/sp/spacer.png",
"charcter2_small_image":"",
"charcter2_position":"",
"command2":"color_fadein(1,1,1,1,0s)",
"effect2":"",
"charcter3_name":"",
"charcter3_big_image":"",
"charcter3_position":"",
"command3":"next(0.5)",
"effect3":"",
"detail":"",
"bg1":"",
"bg2":"",
"log_image":"",
"bgm":"",
"voice":"silent",
"se":"",
"sex":"",
"npc_id":"",
"character_id":"",
"character_flag":"",
"sel1_txt":"",
"sel2_txt":"",
"next":"",
"sel_next1":"",
"sel_next2":"",
"synopsis":""
},
{
"id":"74",
"charcter1_name":"null",
"charcter1_big_image":"/sp/quest/scene/character/body/3030193000_laugh2.png",
"charcter1_small_image":"",
"charcter1_position":"",
"command1":"",
"effect1":"",
"charcter2_name":"",
"charcter2_big_image":"",
"charcter2_small_image":"",
"charcter2_position":"",
"command2":"color_fadein(0,0,0,0,1s)",
"effect2":"",
"charcter3_name":"",
"charcter3_big_image":"",
"charcter3_position":"",
"command3":"next(1)",
"effect3":"",
"detail":"",
"bg1":"/sp/quest/scene/bg/common_20.jpg",
"bg2":"",
"log_image":"",
"bgm":"bgm/75_event_lightly_01.mp3",
"voice":"silent",
"se":"",
"sex":"",
"npc_id":"",
"character_id":"",
"character_flag":"",
"sel1_txt":"",
"sel2_txt":"",
"next":"",
"sel_next1":"",
"sel_next2":"",
"synopsis":""
},
{
"id":"75",
"charcter1_name":"美波",
"charcter1_big_image":"",
"charcter1_small_image":"",
"charcter1_position":"",
"command1":"",
"effect1":"",
"charcter2_name":"",
"charcter2_big_image":"",
"charcter2_small_image":"",
"charcter2_position":"",
"command2":"",
"effect2":"",
"charcter3_name":"",
"charcter3_big_image":"",
"charcter3_position":"",
"command3":"",
"effect3":"",
"detail":"うふふ……
良かったですね！
これでもう大丈夫です！",
"bg1":"",
"bg2":"",
"log_image":"",
"bgm":"",
"voice":"voice/scene_evt170609_cp8_q2_s30_67.mp3",
"se":"",
"sex":"",
"npc_id":"",
"character_id":"",
"character_flag":"",
"sel1_txt":"",
"sel2_txt":"",
"next":"",
"sel_next1":"",
"sel_next2":"",
"synopsis":""
},
{
"id":"76",
"charcter1_name":"桃色の生物",
"charcter1_big_image":"/sp/quest/scene/character/body/3990674000_b2.png",
"charcter1_small_image":"",
"charcter1_position":"C",
"command1":"fadein",
"effect1":"",
"charcter2_name":"",
"charcter2_big_image":"",
"charcter2_small_image":"",
"charcter2_position":"",
"command2":"",
"effect2":"",
"charcter3_name":"",
"charcter3_big_image":"",
"charcter3_position":"",
"command3":"",
"effect3":"",
"detail":"ぴにゃみ！",
"bg1":"",
"bg2":"",
"log_image":"",
"bgm":"",
"voice":"voice/scene_evt170609_cp8_q2_s30_68a.mp3",
"se":"",
"sex":"",
"npc_id":"",
"character_id":"",
"character_flag":"",
"sel1_txt":"",
"sel2_txt":"",
"next":"",
"sel_next1":"",
"sel_next2":"",
"synopsis":""
},
{
"id":"77",
"charcter1_name":"null",
"charcter1_big_image":"",
"charcter1_small_image":"",
"charcter1_position":"",
"command1":"T-slideout",
"effect1":"",
"charcter2_name":"",
"charcter2_big_image":"",
"charcter2_small_image":"",
"charcter2_position":"",
"command2":"next(1)",
"effect2":"",
"charcter3_name":"",
"charcter3_big_image":"",
"charcter3_position":"",
"command3":"flash",
"effect3":"",
"detail":"",
"bg1":"",
"bg2":"",
"log_image":"",
"bgm":"",
"voice":"silent",
"se":"se/job_vee_se_1_6.mp3",
"sex":"",
"npc_id":"",
"character_id":"",
"character_flag":"",
"sel1_txt":"",
"sel2_txt":"",
"next":"",
"sel_next1":"",
"sel_next2":"",
"synopsis":""
},
{
"id":"78",
"charcter1_name":"美波",
"charcter1_big_image":"/sp/spacer.png",
"charcter1_small_image":"",
"charcter1_position":"C",
"command1":"fadein",
"effect1":"",
"charcter2_name":"",
"charcter2_big_image":"/sp/spacer.png",
"charcter2_small_image":"",
"charcter2_position":"L",
"command2":"fadein",
"effect2":"",
"charcter3_name":"",
"charcter3_big_image":"/sp/quest/scene/character/body/3030193000_surprise.png",
"charcter3_position":"R",
"command3":"fadein",
"effect3":"",
"detail":"えっ？",
"bg1":"",
"bg2":"",
"log_image":"",
"bgm":"",
"voice":"voice/scene_evt170609_cp8_q2_s30_69.mp3",
"se":"",
"sex":"",
"npc_id":"",
"character_id":"",
"character_flag":"",
"sel1_txt":"",
"sel2_txt":"",
"next":"",
"sel_next1":"",
"sel_next2":"",
"synopsis":""
},
{
"id":"79",
"charcter1_name":"null",
"charcter1_big_image":"",
"charcter1_small_image":"",
"charcter1_position":"",
"command1":"bg_vibrate_one",
"effect1":"",
"charcter2_name":"",
"charcter2_big_image":"/sp/quest/scene/character/body/3990674000_b2.png",
"charcter2_small_image":"",
"charcter2_position":"L",
"command2":"T-slidein",
"effect2":"",
"charcter3_name":"",
"charcter3_big_image":"",
"charcter3_position":"R",
"command3":"char_vibrate_one",
"effect3":"",
"detail":"美波に向かって勢いよく
抱き着く桃色の生物。",
"bg1":"",
"bg2":"",
"log_image":"",
"bgm":"",
"voice":"silent",
"se":"se/enemy_1200302_se_1.mp3",
"sex":"",
"npc_id":"",
"character_id":"",
"character_flag":"",
"sel1_txt":"",
"sel2_txt":"",
"next":"",
"sel_next1":"",
"sel_next2":"",
"synopsis":""
},
{
"id":"80",
"charcter1_name":"美波",
"charcter1_big_image":"",
"charcter1_small_image":"",
"charcter1_position":"",
"command1":"",
"effect1":"",
"charcter2_name":"",
"charcter2_big_image":"",
"charcter2_small_image":"",
"charcter2_position":"L",
"command2":"",
"effect2":"",
"charcter3_name":"",
"charcter3_big_image":"/sp/quest/scene/character/body/3030193000_surprise.png",
"charcter3_position":"R",
"command3":"jump",
"effect3":"",
"detail":"わっ！
くすぐったいって！",
"bg1":"",
"bg2":"",
"log_image":"",
"bgm":"",
"voice":"voice/scene_evt170609_cp8_q2_s30_71.mp3",
"se":"",
"sex":"",
"npc_id":"",
"character_id":"",
"character_flag":"",
"sel1_txt":"",
"sel2_txt":"",
"next":"",
"sel_next1":"",
"sel_next2":"",
"synopsis":""
},
{
"id":"81",
"charcter1_name":"桃色の生物",
"charcter1_big_image":"",
"charcter1_small_image":"",
"charcter1_position":"",
"command1":"",
"effect1":"",
"charcter2_name":"",
"charcter2_big_image":"",
"charcter2_small_image":"",
"charcter2_position":"L",
"command2":"jump",
"effect2":"",
"charcter3_name":"",
"charcter3_big_image":"",
"charcter3_position":"R",
"command3":"",
"effect3":"",
"detail":"ぴにゃみ！　ぴにゃみ！",
"bg1":"",
"bg2":"",
"log_image":"",
"bgm":"",
"voice":"voice/scene_evt170609_cp8_q2_s30_72a.mp3",
"se":"se/clothes_se_1.mp3",
"sex":"",
"npc_id":"",
"character_id":"",
"character_flag":"",
"sel1_txt":"",
"sel2_txt":"",
"next":"",
"sel_next1":"",
"sel_next2":"",
"synopsis":""
},
{
"id":"82",
"charcter1_name":"美波",
"charcter1_big_image":"",
"charcter1_small_image":"",
"charcter1_position":"",
"command1":"",
"effect1":"",
"charcter2_name":"",
"charcter2_big_image":"",
"charcter2_small_image":"",
"charcter2_position":"",
"command2":"",
"effect2":"",
"charcter3_name":"",
"charcter3_big_image":"/sp/quest/scene/character/body/3030193000_laugh.png",
"charcter3_position":"R",
"command3":"char_vibrate_one",
"effect3":"",
"detail":"あははは！　
くすぐっちゃダメですって！",
"bg1":"",
"bg2":"",
"log_image":"",
"bgm":"",
"voice":"voice/scene_evt170609_cp8_q2_s30_73.mp3",
"se":"",
"sex":"",
"npc_id":"",
"character_id":"",
"character_flag":"",
"sel1_txt":"",
"sel2_txt":"",
"next":"",
"sel_next1":"",
"sel_next2":"",
"synopsis":""
},
{
"id":"83",
"charcter1_name":"志希",
"charcter1_big_image":"/sp/quest/scene/character/body/3030194000_laugh.png",
"charcter1_small_image":"",
"charcter1_position":"C",
"command1":"jump",
"effect1":"",
"charcter2_name":"",
"charcter2_big_image":"/sp/spacer.png",
"charcter2_small_image":"",
"charcter2_position":"",
"command2":"",
"effect2":"",
"charcter3_name":"",
"charcter3_big_image":"/sp/spacer.png",
"charcter3_position":"",
"command3":"",
"effect3":"",
"detail":"にゃははは～！
笑顔が戻ってよかったよかった～！",
"bg1":"",
"bg2":"",
"log_image":"",
"bgm":"",
"voice":"voice/scene_evt170609_cp8_q2_s30_74.mp3",
"se":"",
"sex":"",
"npc_id":"",
"character_id":"",
"character_flag":"",
"sel1_txt":"",
"sel2_txt":"",
"next":"",
"sel_next1":"",
"sel_next2":"",
"synopsis":""
},
{
"id":"84",
"charcter1_name":"ビィ",
"charcter1_big_image":"/sp/quest/scene/character/body/3050001000_mood.png",
"charcter1_small_image":"",
"charcter1_position":"C",
"command1":"jump",
"effect1":"",
"charcter2_name":"",
"charcter2_big_image":"",
"charcter2_small_image":"",
"charcter2_position":"",
"command2":"",
"effect2":"",
"charcter3_name":"",
"charcter3_big_image":"",
"charcter3_position":"",
"command3":"",
"effect3":"",
"detail":"おう、これもふたりの
おかげだぜ！",
"bg1":"",
"bg2":"",
"log_image":"",
"bgm":"",
"voice":"voice/scene_evt170609_cp8_q2_s30_75.mp3",
"se":"",
"sex":"",
"npc_id":"",
"character_id":"",
"character_flag":"",
"sel1_txt":"",
"sel2_txt":"",
"next":"",
"sel_next1":"",
"sel_next2":"",
"synopsis":""
},
{
"id":"85",
"charcter1_name":"ルリア",
"charcter1_big_image":"/sp/quest/scene/character/body/3050000000_laugh.png",
"charcter1_small_image":"",
"charcter1_position":"C",
"command1":"fadein",
"effect1":"",
"charcter2_name":"",
"charcter2_big_image":"",
"charcter2_small_image":"",
"charcter2_position":"",
"command2":"",
"effect2":"",
"charcter3_name":"",
"charcter3_big_image":"",
"charcter3_position":"",
"command3":"",
"effect3":"",
"detail":"うふふ……
良かったですね。
ティード。",
"bg1":"",
"bg2":"",
"log_image":"",
"bgm":"",
"voice":"voice/scene_evt170609_cp8_q2_s30_76.mp3",
"se":"",
"sex":"",
"npc_id":"",
"character_id":"",
"character_flag":"",
"sel1_txt":"",
"sel2_txt":"",
"next":"",
"sel_next1":"",
"sel_next2":"",
"synopsis":""
},
{
"id":"86",
"charcter1_name":"null",
"charcter1_big_image":"",
"charcter1_small_image":"",
"charcter1_position":"",
"command1":"",
"effect1":"",
"charcter2_name":"",
"charcter2_big_image":"",
"charcter2_small_image":"",
"charcter2_position":"",
"command2":"color_fadein(0,0,0,1,2s)",
"effect2":"",
"charcter3_name":"",
"charcter3_big_image":"",
"charcter3_position":"",
"command3":"",
"effect3":"",
"detail":"こうして、全空を巻き込んだ
ぴにゃビ化事件は、
解決を見せたのだった。",
"bg1":"",
"bg2":"",
"log_image":"",
"bgm":"bgm/75_event_lightly_05.mp3",
"voice":"silent",
"se":"",
"sex":"",
"npc_id":"",
"character_id":"",
"character_flag":"",
"sel1_txt":"",
"sel2_txt":"",
"next":"",
"sel_next1":"",
"sel_next2":"",
"synopsis":""
},
{
"id":"87",
"charcter1_name":"null",
"charcter1_big_image":"",
"charcter1_small_image":"",
"charcter1_position":"",
"command1":"",
"effect1":"",
"charcter2_name":"",
"charcter2_big_image":"",
"charcter2_small_image":"",
"charcter2_position":"",
"command2":"color_fadein(0,1,0,1,0s)",
"effect2":"",
"charcter3_name":"",
"charcter3_big_image":"",
"charcter3_position":"",
"command3":"",
"effect3":"",
"detail":"新田美波と一ノ瀬志希の二人の名は、
未曽有の危機を救ったアイドルとして
瞬く間に全空に広まったという。",
"bg1":"",
"bg2":"",
"log_image":"",
"bgm":"",
"voice":"silent",
"se":"",
"sex":"",
"npc_id":"",
"character_id":"",
"character_flag":"",
"sel1_txt":"",
"sel2_txt":"",
"next":"",
"sel_next1":"",
"sel_next2":"",
"synopsis":""
}
],
"move_scrapbook_detail":false,
"popup_style_type":"",
"choice_image":""
}